kl_kernel_logic/__init__.py
kl_kernel_logic/cael.py
kl_kernel_logic/kernel.py
kl_kernel_logic/psi.py
kl_kernel_logic/examples/__init__.py
kl_kernel_logic/examples/text_simplify.py
kl_kernel_logic/examples_foundations/__init__.py
kl_kernel_logic/examples_foundations/operations.py
kl_kernel_logic/examples_foundations/runners.py
kl_kernel_logic-0.5.0.dist-info/licenses/LICENSE
kl_kernel_logic-0.5.0.dist-info/METADATA
kl_kernel_logic-0.5.0.dist-info/WHEEL
kl_kernel_logic-0.5.0.dist-info/top_level.txt
kl_kernel_logic-0.5.0.dist-info/RECORD
