Metadata-Version: 2.4
Name: kl-kernel-logic
Version: 0.5.0
Summary: Lightweight deterministic execution substrate for governed operations.
Author-email: Lukas Pfister <228201683+lukaspfisterch@users.noreply.github.com>
License: MIT
Project-URL: Homepage, https://github.com/lukaspfisterch/kl-kernel-logic
Project-URL: Repository, https://github.com/lukaspfisterch/kl-kernel-logic
Project-URL: Issues, https://github.com/lukaspfisterch/kl-kernel-logic/issues
Project-URL: Changelog, https://github.com/lukaspfisterch/kl-kernel-logic/blob/main/CHANGELOG.md
Keywords: deterministic,execution,governance,audit,llm,kernel,policy,traceability
Classifier: Development Status :: 3 - Alpha
Classifier: Intended Audience :: Developers
Classifier: Intended Audience :: Information Technology
Classifier: License :: OSI Approved :: MIT License
Classifier: Operating System :: OS Independent
Classifier: Programming Language :: Python :: 3
Classifier: Programming Language :: Python :: 3 :: Only
Classifier: Programming Language :: Python :: 3.10
Classifier: Programming Language :: Python :: 3.11
Classifier: Programming Language :: Python :: 3.12
Classifier: Topic :: Software Development :: Libraries
Classifier: Topic :: System :: Monitoring
Classifier: Topic :: Security
Requires-Python: >=3.11
License-File: LICENSE
Provides-Extra: dev
Requires-Dist: pytest; extra == "dev"
Requires-Dist: pytest-cov; extra == "dev"
Dynamic: license-file
